django_photobooth_widget/__init__.py
django_photobooth_widget/widgets.py
django_photobooth_widget/static/photobooth_widget/css/photobooth_widget.css
django_photobooth_widget/static/photobooth_widget/js/photobooth.js
django_photobooth_widget/static/photobooth_widget/js/photobooth_activate.js
django_photobooth_widget/static/photobooth_widget/js/photobooth_min.js
django_photobooth_widget/templates/photobooth_widget/photobooth_widget.html
django_photobooth_widget-0.1.1.dist-info/METADATA
django_photobooth_widget-0.1.1.dist-info/WHEEL
django_photobooth_widget-0.1.1.dist-info/top_level.txt
django_photobooth_widget-0.1.1.dist-info/RECORD
